MANIFEST.in
README.md
setup.cfg
setup.py
versioneer.py
py_spi.egg-info/PKG-INFO
py_spi.egg-info/SOURCES.txt
py_spi.egg-info/dependency_links.txt
py_spi.egg-info/requires.txt
py_spi.egg-info/top_level.txt
pyspi/SPILike.py
pyspi/__init__.py
pyspi/__version__.py
pyspi/_version.py
pyspi/io/__init__.py
pyspi/io/file_utils.py
pyspi/io/get_files.py
pyspi/io/package_data.py
pyspi/io/plotting/__init__.py
pyspi/io/plotting/spi_display.py
pyspi/test/__init__.py
pyspi/test/test_active_dets.py
pyspi/test/test_download.py
pyspi/test/test_grb_fit.py
pyspi/test/test_packagedata.py
pyspi/test/test_response.py
pyspi/test/test_spipointing.py
pyspi/test/test_time_series.py
pyspi/utils/__init__.py
pyspi/utils/function_utils.py
pyspi/utils/geometry.py
pyspi/utils/livedets.py
pyspi/utils/data_builder/__init__.py
pyspi/utils/data_builder/time_series_builder.py
pyspi/utils/response/__init__.py
pyspi/utils/response/spi_drm.py
pyspi/utils/response/spi_frame.py
pyspi/utils/response/spi_pointing.py
pyspi/utils/response/spi_response.py
pyspi/utils/response/spi_response_data.py