Metadata-Version: 2.1
Name: py-spi
Version: 1.0.0
Summary: A python analysis framework for INTEGRAL-SPI
Home-page: https://github.com/grburgess/pyspi
Author: Bjoern Biltzinger
Author-email: bbiltzing@mpe.mpg.de
License: GPL-3+
Project-URL: Bug Tracker, https://github.com/BjoernBiltzinger/pyspi/issues
Project-URL: Source Code, https://github.com/BjoernBiltzinger/pyspi
Platform: UNKNOWN
Classifier: Development Status :: 5 - Production/Stable
Classifier: Environment :: Console
Classifier: Intended Audience :: Science/Research
Classifier: License :: OSI Approved :: GNU General Public License v3 or later (GPLv3+)
Classifier: Operating System :: POSIX
Classifier: Programming Language :: Python :: 3.7
Classifier: Programming Language :: Python :: 3.8
Classifier: Programming Language :: Python :: 3.9
Classifier: Topic :: Scientific/Engineering :: Physics
